Rmoney_bhavcopy/Bhavcopy_Reteriver.py
Rmoney_bhavcopy/__init__.py
Rmoney_bhavcopy/config.py
Rmoney_bhavcopy/py.typed
Rmoney_bhavcopy/test.py
rmoney_bhavcopy-0.1.3.dist-info/METADATA
rmoney_bhavcopy-0.1.3.dist-info/WHEEL
rmoney_bhavcopy-0.1.3.dist-info/RECORD
