Metadata-Version: 2.4
Name: Rmoney_bhavcopy
Version: 0.1.3
Summary: This Python Library is designed to fetch BhavCopy data (daily market reports) from a PostgreSQL database for specified symbols, date ranges, and series. The script provides utility functions to standardize data formats, parse dates, and retrieve data for Cash Market (CM), Futures and Options (FO), and Indices.
Project-URL: Homepage, https://github.com/DeepanshuMangolia/RMoney_Bhavcopy
Author-email: "deepanshu.mangolia" <deepanshu.mangolia@rmoneyindia.com>
Requires-Python: >=3.12
Requires-Dist: pandas>=2.2.3
Requires-Dist: psycopg2>=2.9.10
Requires-Dist: python-dotenv>=1.0.1
